hic_ssdna/__init__.py
hic_ssdna/contacts_filter.py
hic_ssdna/oligos_replacement.py
tests/__init__.py
tests/check_outputs.py
tests/test_oligo_file_correction.py
tests/test_oligo_replacement.py
tests/tests_replacement.py
hic_ssdna-1.1.0.dist-info/LICENSE
hic_ssdna-1.1.0.dist-info/METADATA
hic_ssdna-1.1.0.dist-info/WHEEL
hic_ssdna-1.1.0.dist-info/entry_points.txt
hic_ssdna-1.1.0.dist-info/top_level.txt
hic_ssdna-1.1.0.dist-info/RECORD
