Metadata-Version: 2.1
Name: hic-ssdna
Version: 1.1.0
Summary: A package to ananlyze the data generated by Hi-C Capture for ssDNA
Home-page: https://gitbio.ens-lyon.fr/LBMC/GM/hic-ssdna
Author: Loqmen Anani
Author-email: loqmen.anani@ens-lyon.fr
Classifier: License :: OSI Approved :: GNU General Public License v3 (GPLv3)
Classifier: Programming Language :: Python :: 3
Classifier: Operating System :: OS Independent
License-File: LICENSE
Requires-Dist: pandas
